humans_mariyasha/__init__.py
humans_mariyasha-0.0.2.dist-info/METADATA
humans_mariyasha-0.0.2.dist-info/WHEEL
humans_mariyasha-0.0.2.dist-info/licenses/LICENSE
humans_mariyasha-0.0.2.dist-info/RECORD
