Metadata-Version: 2.3
Name: humans_mariyasha
Version: 0.0.2
Summary: collection of biblical humans and their family relations
Project-URL: Homepage, https://github.com/MariyaSha/humans
Project-URL: Issues, https://github.com/MariyaSha/humans
Author-email: Mariya Sha <mariya@pythonsimplified.org>
Classifier: License :: OSI Approved :: GNU General Public License v2 (GPLv2)
Classifier: Operating System :: OS Independent
Classifier: Programming Language :: Python :: 3
Requires-Python: >=3.0
